{
	"bodies": [
		{
			"agricultural": "f0/0",
			"argOfPeriapsis": "f0/0",
			"aspectRatio": "f1/0",
			"atmosColor": [
				0,
				0,
				0,
				255
			],
			"atmosDensity": "f0/0",
			"atmosOxidizing": "f0/0",
			"averageTemp": 3384,
			"axialTilt": "f0/0",
			"children": [
				1
			],
			"eccentricity": "f0/0",
			"hasRings": false,
			"humanActivity": "f0/0",
			"inclination": "f0/0",
			"life": "f0/0",
			"mass": "f0/3822520893",
			"metallicity": "f0/0",
			"name": "Lorirak",
			"orbitalOffset": "f0/0",
			"orbitalPhase": "f0/0",
			"population": "f0/0",
			"radius": "f24/1760936591",
			"rotationPeriod": "f0/0",
			"rotationPhase": "f0/0",
			"seed": 1168705109,
			"semiMajorAxis": "f0/0",
			"type": "STAR_M_GIANT",
			"volatileIces": "f0/0",
			"volatileLiquid": "f0/0",
			"volcanicity": "f0/0"
		},
		{
			"agricultural": "f0/0",
			"argOfPeriapsis": "f1/378476587",
			"aspectRatio": "f1/0",
			"atmosColor": [
				255,
				255,
				255,
				3
			],
			"atmosDensity": "f1/744559452",
			"atmosOxidizing": "f0/51835802",
			"averageTemp": 316,
			"axialTilt": "f0/17055972",
			"children": [
				2,
				3,
				4
			],
			"eccentricity": "f0/177034134",
			"hasRings": true,
			"humanActivity": "f0/0",
			"inclination": "f0/1069319914",
			"life": "f0/0",
			"mass": "f75/1752404110",
			"metallicity": "f0/2648754496",
			"name": "Lorirak a",
			"orbitalOffset": "f5/865247718",
			"orbitalPhase": "f5/3543582639",
			"parent": 0,
			"population": "f0/0",
			"radius": "f8/2148061689",
			"ringsBaseColor": [
				111,
				119,
				84,
				222
			],
			"ringsMaxRadius": "f1/2777304250",
			"ringsMinRadius": "f1/1052501233",
			"rotationPeriod": "f6/894784853",
			"rotationPhase": "f0/0",
			"seed": 4281581978,
			"semiMajorAxis": "f6/2170331739",
			"type": "PLANET_GAS_GIANT",
			"volatileIces": "f0/0",
			"volatileLiquid": "f0/0",
			"volcanicity": "f0/953644558"
		},
		{
			"agricultural": "f0/0",
			"argOfPeriapsis": "f4294967293/3908400245",
			"aspectRatio": "f1/0",
			"atmosColor": [
				0,
				0,
				0,
				0
			],
			"atmosDensity": "f0/0",
			"atmosOxidizing": "f0/1739709838",
			"averageTemp": 316,
			"axialTilt": "f0/840445150",
			"eccentricity": "f0/301013517",
			"hasRings": false,
			"humanActivity": "f0/0",
			"inclination": "f0/1014554248",
			"life": "f0/0",
			"mass": "f0/90677078",
			"metallicity": "f0/1358345864",
			"name": "Lorirak a 1",
			"orbitalOffset": "f4/217815717",
			"orbitalPhase": "f0/3805688576",
			"parent": 1,
			"population": "f0/0",
			"radius": "f0/1174359139",
			"rotationPeriod": "f7/894784853",
			"rotationPhase": "f0/0",
			"seed": 2303013420,
			"semiMajorAxis": "f0/152828362",
			"type": "PLANET_TERRESTRIAL",
			"volatileIces": "f0/0",
			"volatileLiquid": "f0/0",
			"volcanicity": "f0/560091"
		},
		{
			"agricultural": "f0/0",
			"argOfPeriapsis": "f1/1886301197",
			"aspectRatio": "f1/0",
			"atmosColor": [
				0,
				0,
				0,
				0
			],
			"atmosDensity": "f0/0",
			"atmosOxidizing": "f0/3717741818",
			"averageTemp": 316,
			"axialTilt": "f0/645132985",
			"eccentricity": "f0/6628642",
			"hasRings": false,
			"humanActivity": "f0/0",
			"inclination": "f0/1388751215",
			"life": "f0/0",
			"mass": "f0/55875054",
			"metallicity": "f0/1426058234",
			"name": "Lorirak a 2",
			"orbitalOffset": "f2/1916764152",
			"orbitalPhase": "f1/504630837",
			"parent": 1,
			"population": "f0/0",
			"radius": "f0/1159122172",
			"rotationPeriod": "f7/4116010325",
			"rotationPhase": "f0/0",
			"seed": 1399719238,
			"semiMajorAxis": "f0/226212511",
			"type": "PLANET_TERRESTRIAL",
			"volatileIces": "f0/0",
			"volatileLiquid": "f0/0",
			"volcanicity": "f0/52925591"
		},
		{
			"agricultural": "f0/0",
			"argOfPeriapsis": "f0/2251437429",
			"aspectRatio": "f1/0",
			"atmosColor": [
				0,
				0,
				0,
				0
			],
			"atmosDensity": "f0/0",
			"atmosOxidizing": "f0/2168168255",
			"averageTemp": 316,
			"axialTilt": "f0/589955021",
			"children": [
				5
			],
			"eccentricity": "f0/3744075",
			"hasRings": false,
			"humanActivity": "f0/0",
			"inclination": "f0/372694021",
			"life": "f0/0",
			"mass": "f0/784530",
			"metallicity": "f0/3047001905",
			"name": "Dixon XIX",
			"orbitalOffset": "f1/671440315",
			"orbitalPhase": "f0/1708190130",
			"parent": 1,
			"population": "f0/2094495963",
			"radius": "f0/219169833",
			"rotationPeriod": "f4/1789569706",
			"rotationPhase": "f0/0",
			"seed": 521277694,
			"semiMajorAxis": "f0/279228260",
			"type": "PLANET_TERRESTRIAL",
			"volatileIces": "f0/0",
			"volatileLiquid": "f0/0",
			"volcanicity": "f0/272295"
		},
		{
			"agricultural": "f0/0",
			"argOfPeriapsis": "f0/0",
			"aspectRatio": "f1/0",
			"atmosColor": [
				0,
				0,
				0,
				255
			],
			"atmosDensity": "f0/0",
			"atmosOxidizing": "f0/0",
			"averageTemp": 316,
			"axialTilt": "f0/0",
			"eccentricity": "f0/0",
			"hasRings": false,
			"humanActivity": "f0/0",
			"inclination": "f0/3112799807",
			"life": "f0/0",
			"mass": "f0/0",
			"metallicity": "f0/0",
			"name": "Port Donaldson",
			"orbitalOffset": "f6/542190038",
			"orbitalPhase": "f0/0",
			"parent": 4,
			"population": "f0/955758",
			"radius": "f0/0",
			"rotationPeriod": "f0/0",
			"rotationPhase": "f0/0",
			"seed": 238412583,
			"semiMajorAxis": "f0/0",
			"type": "STARPORT_SURFACE",
			"volatileIces": "f0/0",
			"volatileLiquid": "f0/0",
			"volcanicity": "f0/0"
		}
	],
	"explored": true,
	"faction": "Independent Faction",
	"govType": "LIBDEM",
	"lawlessness": "f0/951644861",
	"longDesc": "",
	"name": "Lorirak",
	"pos": [
		6.350828647613525,
		7.995015621185303,
		4.384050369262695
	],
	"root": 0,
	"sector": [
		-49,
		-30,
		-30
	],
	"seed": 536667733,
	"shortDesc": "Mining colony.",
	"stars": [
		"STAR_M_GIANT"
	]
}
